frontier_council/__init__.py
frontier_council/cli.py
frontier_council/council.py
frontier_council-0.1.3.dist-info/METADATA
frontier_council-0.1.3.dist-info/WHEEL
frontier_council-0.1.3.dist-info/entry_points.txt
frontier_council-0.1.3.dist-info/licenses/LICENSE
frontier_council-0.1.3.dist-info/RECORD
