Metadata-Version: 2.4
Name: frontier-council
Version: 0.1.3
Summary: Multi-model deliberation for important decisions. 5 frontier LLMs debate, then a judge synthesizes consensus.
Project-URL: Homepage, https://github.com/terry-li-hm/frontier-council
Project-URL: Repository, https://github.com/terry-li-hm/frontier-council
Project-URL: Issues, https://github.com/terry-li-hm/frontier-council/issues
Author-email: Terry Li <terry.li.hm@gmail.com>
License-Expression: MIT
License-File: LICENSE
Keywords: ai,council,debate,deliberation,frontier,llm,multi-model,openrouter
Classifier: Development Status :: 4 - Beta
Classifier: Environment :: Console
Classifier: Intended Audience :: Developers
Classifier: License :: OSI Approved :: MIT License
Classifier: Programming Language :: Python :: 3
Classifier: Programming Language :: Python :: 3.11
Classifier: Programming Language :: Python :: 3.12
Classifier: Topic :: Scientific/Engineering :: Artificial Intelligence
Requires-Python: >=3.11
Requires-Dist: httpx>=0.25.0
